opencosmo/__init__.py
opencosmo/analysis/__init__.py
opencosmo/analysis/cli.py
opencosmo/analysis/diffsky.py
opencosmo/analysis/install/__init__.py
opencosmo/analysis/install/install.py
opencosmo/analysis/install/source.py
opencosmo/analysis/install/specs/__init__.py
opencosmo/analysis/install/specs/diffsky.json
opencosmo/analysis/install/specs/vizualize.json
opencosmo/analysis/install/versions.py
opencosmo/analysis/yt_utils.py
opencosmo/analysis/yt_viz.py
opencosmo/collection/__init__.py
opencosmo/collection/io.py
opencosmo/collection/lightcone/__init__.py
opencosmo/collection/lightcone/healpix_map.py
opencosmo/collection/lightcone/lightcone.py
opencosmo/collection/lightcone/stack.py
opencosmo/collection/protocols.py
opencosmo/collection/simulation/__init__.py
opencosmo/collection/simulation/simulation.py
opencosmo/collection/structure/__init__.py
opencosmo/collection/structure/evaluate.py
opencosmo/collection/structure/handler.py
opencosmo/collection/structure/io.py
opencosmo/collection/structure/structure.py
opencosmo/column/__init__.py
opencosmo/column/cache.py
opencosmo/column/column.py
opencosmo/column/evaluate.py
opencosmo/column/stock.py
opencosmo/cosmology.py
opencosmo/dataset/__init__.py
opencosmo/dataset/build.py
opencosmo/dataset/dataset.py
opencosmo/dataset/derived.py
opencosmo/dataset/evaluate.py
opencosmo/dataset/formats.py
opencosmo/dataset/handler.py
opencosmo/dataset/im.py
opencosmo/dataset/mpi.py
opencosmo/dataset/state.py
opencosmo/evaluate.py
opencosmo/file.py
opencosmo/header.py
opencosmo/index/__init__.py
opencosmo/index/build.py
opencosmo/index/get.py
opencosmo/index/in_range.py
opencosmo/index/mask.py
opencosmo/index/project.py
opencosmo/index/take.py
opencosmo/index/unary.py
opencosmo/io/__init__.py
opencosmo/io/file.py
opencosmo/io/io.py
opencosmo/io/mpi.py
opencosmo/io/parquet.py
opencosmo/io/protocols.py
opencosmo/io/schema.py
opencosmo/io/serial.py
opencosmo/io/updaters.py
opencosmo/io/verify.py
opencosmo/io/writer.py
opencosmo/mpi.py
opencosmo-1.0.3.dist-info/WHEEL
opencosmo-1.0.3.dist-info/entry_points.txt
opencosmo-1.0.3.dist-info/METADATA
opencosmo-1.0.3.dist-info/RECORD
