Metadata-Version: 2.3
Name: opencosmo
Version: 1.0.3
Summary: OpenCosmo Python Toolkit
Author: Patrick Wells, Will Hicks, Patricia Larsen, Michael Buehlmann
Author-email: Patrick Wells <pwells@anl.gov>, Will Hicks <whicks@anl.gov>, Patricia Larsen <prlarsen@anl.gov>, Michael Buehlmann <mbuehlmann@anl.gov>
Requires-Dist: h5py>=3.12.1,<4.0.0
Requires-Dist: astropy>=7.2.0,<8.0.0
Requires-Dist: pydantic>=2.10.6,<3.0.0
Requires-Dist: hdf5plugin>=5.0.0,<6.0.0
Requires-Dist: healpy>=1.18.1,<2.0.0
Requires-Dist: healsparse==1.11.1
Requires-Dist: deprecated>=1.2.18,<2.0.0
Requires-Dist: numpy>=2.0,<2.4
Requires-Dist: click>=8.2.1,<9.0.0
Requires-Dist: numba>=0.62.1
Requires-Dist: rustworkx>=0.17.1
Requires-Dist: pyarrow>=21.0.0 ; extra == 'io'
Requires-Python: >=3.11, <3.15
Provides-Extra: io
